extra_validator/__init__.py
extra_validator/apps.py
extra_validator/field_validation/__init__.py
extra_validator/field_validation/validator.py
django_extra_field_validation-1.2.3.dist-info/LICENSE-APACHE
django_extra_field_validation-1.2.3.dist-info/LICENSE-MIT
django_extra_field_validation-1.2.3.dist-info/METADATA
django_extra_field_validation-1.2.3.dist-info/WHEEL
django_extra_field_validation-1.2.3.dist-info/top_level.txt
django_extra_field_validation-1.2.3.dist-info/RECORD
